{
  "logo": "Ed Barlow",
  "name": "Ed Barlow",
  "tagline": "Software engineer, database architect, and published author. Building thoughtful systems for complex problems.",
  "email": "edward.m.barlow@gmail.com",
  "phone": "(914) 837-4798",
  "phone_e164": "+19148374798",
  "copyright": "Web Cloud Studio — Ed Barlow",
  "section_title": "My Projects",
  "section_subtitle": "",
  "home_html": "<h2>AI Enabled Hands-On Technology Leader looking for work</h2>\n<h2>Current Project:  Family and Friends Shared Code Platform</h2>\n<p>I am combining my <a href=\"https://www.amazon.com/Process-Based-Database-Administration-Management-ebook/dp/B073RRQBZC\">Process Based Methodology</a> and scale-proven <a href=\"https://webcloudstudio.github.io/webcloudstudio/project-docs/Specifications/Features.html\">Technology Rules</a> into a \nFree Product enabling seamlessly/secure capability sharing within a group (family, friends, team)</p>\n<p>Contact me if you want to know more or to collaborate.</p>\n<p>The concept is exciting.  </p>\n<p>I can automatically conform with code projects you write to work within a framework, to carefully expose the capabilities in your <strong>Circle of Trust</strong>, to share resources, project data, and personal data with only those\nyou trust.  </p>\n<p>The platform lets you share the exciting things we can now do with those you trust.</p>\n<ul>\n<li><strong>Control Panel</strong> - Unified project view (namespaced) plus project control</li>\n<li><strong>Capabilities</strong> - Transport agnostic capabilities provide Interoperability (Rest, CLI, Async, MCP)</li>\n<li><strong>Full Developer Platform</strong> - Consistent Builds, Context Optimized, You Control</li>\n<li><strong>Formal Workflow</strong> - Change control using Light-weight ticketing system (kanban)</li>\n<li><strong>Seamless Operations</strong> - Monitoring, Documentation, Scheduled tasks, and Data Flows</li>\n</ul>\n<p><strong>Hands On Leader</strong> at hedge funds, investment banks, insurance companies, and startups </p>\n<p><strong>Author</strong>, <strong>Speaker</strong>, <strong>Free Software Developer</strong></p>"
}